odoo9_addon_stock_account_quant_merge-9.0.1.0.0-py2.7-nspkg.pth
odoo9_addon_stock_account_quant_merge-9.0.1.0.0.dist-info/top_level.txt
odoo9_addon_stock_account_quant_merge-9.0.1.0.0.dist-info/WHEEL
odoo9_addon_stock_account_quant_merge-9.0.1.0.0.dist-info/RECORD
odoo9_addon_stock_account_quant_merge-9.0.1.0.0.dist-info/metadata.json
odoo9_addon_stock_account_quant_merge-9.0.1.0.0.dist-info/DESCRIPTION.rst
odoo9_addon_stock_account_quant_merge-9.0.1.0.0.dist-info/METADATA
odoo9_addon_stock_account_quant_merge-9.0.1.0.0.dist-info/namespace_packages.txt
odoo_addons/stock_account_quant_merge/__openerp__.py
odoo_addons/stock_account_quant_merge/__init__.py
odoo_addons/stock_account_quant_merge/README.rst
odoo_addons/stock_account_quant_merge/models/stock.py
odoo_addons/stock_account_quant_merge/models/__init__.py
odoo_addons/stock_account_quant_merge/i18n/it.po
odoo_addons/stock_account_quant_merge/i18n/es.po
odoo_addons/stock_account_quant_merge/i18n/ro.po
odoo_addons/stock_account_quant_merge/i18n/sl.po
odoo_addons/stock_account_quant_merge/i18n/de.po
odoo_addons/stock_account_quant_merge/i18n/fr.po
odoo_addons/stock_account_quant_merge/i18n/pt_BR.po
odoo_addons/stock_account_quant_merge/i18n/fi.po
odoo_addons/stock_account_quant_merge/tests/__init__.py
odoo_addons/stock_account_quant_merge/tests/test_merge.py
